setup.py
django_s3fileup.egg-info/PKG-INFO
django_s3fileup.egg-info/SOURCES.txt
django_s3fileup.egg-info/dependency_links.txt
django_s3fileup.egg-info/not-zip-safe
django_s3fileup.egg-info/requires.txt
django_s3fileup.egg-info/top_level.txt
s3fileup/__init__.py
s3fileup/models.py
s3fileup/settings.py
s3fileup/urls.py
s3fileup/utils.py
s3fileup/api/__init__.py
s3fileup/api/resources.py
s3fileup/api/views.py