Metadata-Version: 1.0
Name: django-s3fileup
Version: 0.5
Summary: Django app that exposes a file upload API to S3, direct from the client
Home-page: http://github.com/roadhead/s3fileup
Author: Rohit Sankaran
Author-email: rohit@riot.io
License: UNKNOWN
Platform: UNKNOWN
Classifier: Framework :: Django
Classifier: Intended Audience :: Developers
Classifier: Intended Audience :: System Administrators
Classifier: Operating System :: OS Independent
Classifier: Topic :: Software Development
